Metadata-Version: 2.1
Name: dsboot
Version: 1.0.0
Summary: Generate signaling records for Authenticated DNSSEC Bootstrapping from existing zones.
Home-page: https://github.com/desec-io/dsboot
Author: Peter Thomassen
Author-email: peter@desec.io
Classifier: Development Status :: 5 - Production/Stable
Classifier: Intended Audience :: Developers
Classifier: Programming Language :: Python :: 3
Classifier: License :: OSI Approved :: MIT License
Classifier: Topic :: Internet :: Name Service (DNS)
License-File: LICENSE
Requires-Dist: dnspython>=2.6.1
